README.md
setup.py
clex/__init__.py
clex/clex.py
clex.egg-info/PKG-INFO
clex.egg-info/SOURCES.txt
clex.egg-info/dependency_links.txt
clex.egg-info/requires.txt
clex.egg-info/top_level.txt