Metadata-Version: 1.2
Name: clex
Version: 0.0.1
Summary: C lexical analysis
Home-page: https://github.com/yuvalino/python-clex
Author: Yuval
Author-email: yuvalino@gmail.com
License: UNKNOWN
Project-URL: Source Code, https://github.com/yuvalino/python-clex
Platform: UNKNOWN
Classifier: Programming Language :: Python
